{
  "BBH": {
    "mass_1": {
      "type": "zscore",
      "mean": 33.304613576598086,
      "std": 15.301911399251775
    },
    "mass_2": {
      "type": "zscore",
      "mean": 20.030317482533054,
      "std": 12.271846702126854
    },
    "total_mass": {
      "type": "zscore",
      "mean": 53.334931059131144,
      "std": 24.683895901022964
    },
    "chirp_mass": {
      "type": "zscore",
      "mean": 21.56804496242566,
      "std": 10.793852015958485
    },
    "luminosity_distance": {
      "type": "log",
      "min": 4.7602005286011115,
      "max": 7.600828692553471
    },
    "a1": {
      "type": "tanh",
      "min": 0.0020769489068558074,
      "max": 0.8250310818805614
    },
    "a2": {
      "type": "tanh",
      "min": 0.003962253376496816,
      "max": 0.8208242329491267
    },
    "theta_jn": {
      "type": "angle"
    },
    "ra": {
      "type": "angle"
    },
    "dec": {
      "type": "angle"
    },
    "psi": {
      "type": "angle"
    },
    "phase": {
      "type": "angle"
    }
  },
  "BNS": {
    "mass_1": {
      "type": "zscore",
      "mean": 1.4889854115925383,
      "std": 0.13761139926875046
    },
    "mass_2": {
      "type": "zscore",
      "mean": 1.2954897324358217,
      "std": 0.14406381365282575
    },
    "total_mass": {
      "type": "zscore",
      "mean": 2.78447514402836,
      "std": 0.245371545407279
    },
    "chirp_mass": {
      "type": "zscore",
      "mean": 1.206640670213533,
      "std": 0.10749689650073699
    },
    "luminosity_distance": {
      "type": "log",
      "min": 3.697721744809745,
      "max": 5.703181960636222
    },
    "a1": {
      "type": "tanh",
      "min": 6.545205046154523e-05,
      "max": 0.04975264895230539
    },
    "a2": {
      "type": "tanh",
      "min": 0.00012946093793880786,
      "max": 0.0499786770899213
    },
    "theta_jn": {
      "type": "angle"
    },
    "ra": {
      "type": "angle"
    },
    "dec": {
      "type": "angle"
    },
    "psi": {
      "type": "angle"
    },
    "phase": {
      "type": "angle"
    }
  },
  "NSBH": {
    "mass_1": {
      "type": "zscore",
      "mean": 30.029140533911065,
      "std": 23.29777938209405
    },
    "mass_2": {
      "type": "zscore",
      "mean": 1.6022866618338423,
      "std": 0.21679198597765104
    },
    "total_mass": {
      "type": "zscore",
      "mean": 31.631427195744912,
      "std": 23.286382227750483
    },
    "chirp_mass": {
      "type": "zscore",
      "mean": 4.685463797019856,
      "std": 1.69490535255236
    },
    "luminosity_distance": {
      "type": "log",
      "min": 5.11804771761467,
      "max": 6.681267084976647
    },
    "a1": {
      "type": "tanh",
      "min": 0.0,
      "max": 0.9718757087907154
    },
    "a2": {
      "type": "tanh",
      "min": 2.3499268020976682e-05,
      "max": 0.0498968474720056
    },
    "theta_jn": {
      "type": "angle"
    },
    "ra": {
      "type": "angle"
    },
    "dec": {
      "type": "angle"
    },
    "psi": {
      "type": "angle"
    },
    "phase": {
      "type": "angle"
    }
  }
}